consolidation/__init__.py
consolidation/attribute_mapping.py
consolidation/carrier_integration_base.py
consolidation/common_config.py
consolidation/airwayscourier/__init__.py
consolidation/airwayscourier/airwayscourier.py
consolidation/blitz/__init__.py
consolidation/blitz/blitz.py
consolidation/utilization/__init__.py
consolidation/utilization/db_operations.py
consolidation/utilization/final_order_db_updator.py
consolidation/utilization/generic_order_id_generator.py
consolidation/utilization/get_awb.py
consolidation/utilization/pdf_merger.py
consolidation/utilization/pdf_split.py
consolidation/utilization/s3_aws_ops.py
consolidation/utilization/timed_cache.py
consolidation/utilization/utils.py
consolidation/utilization/utils2.py
carrier_integration_pack-0.1.0.dist-info/METADATA
carrier_integration_pack-0.1.0.dist-info/WHEEL
carrier_integration_pack-0.1.0.dist-info/top_level.txt
carrier_integration_pack-0.1.0.dist-info/RECORD
