Metadata-Version: 2.1
Name: carrier-integration-pack
Version: 0.1.0
Summary: UNKNOWN
Home-page: UNKNOWN
License: UNKNOWN
Platform: UNKNOWN
Requires-Dist: blinker==1.8.2
Requires-Dist: boto==2.49.0
Requires-Dist: certifi==2024.8.30
Requires-Dist: charset-normalizer==3.4.0
Requires-Dist: click==8.1.7
Requires-Dist: colorama==0.4.6
Requires-Dist: python-dateutil
Requires-Dist: dnspython==2.6.1
Requires-Dist: Flask==3.0.3
Requires-Dist: idna==3.10
Requires-Dist: importlib-metadata==8.5.0
Requires-Dist: itsdangerous==2.2.0
Requires-Dist: Jinja2==3.1.5
Requires-Dist: MarkupSafe==2.1.5
Requires-Dist: pdfkit==1.0.0
Requires-Dist: pymongo==4.10.1
Requires-Dist: pypdf==5.1.0
Requires-Dist: pytz==2024.2
Requires-Dist: PyYAML==6.0.2
Requires-Dist: requests==2.32.3
Requires-Dist: strgen==1.3.1
Requires-Dist: typing-extensions==4.12.2
Requires-Dist: urllib3==2.2.3
Requires-Dist: Werkzeug==3.0.6
Requires-Dist: zipp==3.20.2
Requires-Dist: curlify
